joint_calling/__init__.py
joint_calling/_version.py
joint_calling/dataproc.py
joint_calling/filter_cutoffs.yaml
joint_calling/hard_filtering.py
joint_calling/joint_genotyping.py
joint_calling/mt_to_vcf.py
joint_calling/pop_strat_qc.py
joint_calling/pre_combiner.py
joint_calling/resources.py
joint_calling/sample_qc.py
joint_calling/sm_utils.py
joint_calling/upload_processor.py
joint_calling/utils.py
joint_calling/variant_qc.py
joint_calling/vep-config.json
joint_calling/vqsr.py
joint_calling/__pycache__/__init__.cpython-36.pyc
joint_calling/__pycache__/__init__.cpython-37.pyc
joint_calling/__pycache__/__init__.cpython-39.pyc
joint_calling/__pycache__/_version.cpython-37.pyc
joint_calling/__pycache__/hard_filtering.cpython-37.pyc
joint_calling/__pycache__/mt_to_vcf.cpython-37.pyc
joint_calling/__pycache__/pop_strat_qc.cpython-37.pyc
joint_calling/__pycache__/utils.cpython-37.pyc
joint_calling/__pycache__/vqsr.cpython-37.pyc
joint_calling-0.4.39.data/scripts/ancestry_pca.py
joint_calling-0.4.39.data/scripts/ancestry_plot.py
joint_calling-0.4.39.data/scripts/annotate_as.py
joint_calling-0.4.39.data/scripts/check_pedigree.py
joint_calling-0.4.39.data/scripts/combine_gvcfs.py
joint_calling-0.4.39.data/scripts/create_rf_annotations.py
joint_calling-0.4.39.data/scripts/evaluation.py
joint_calling-0.4.39.data/scripts/final_filter.py
joint_calling-0.4.39.data/scripts/final_mt_to_vcf.py
joint_calling-0.4.39.data/scripts/generate_freq_data.py
joint_calling-0.4.39.data/scripts/generate_info_ht.py
joint_calling-0.4.39.data/scripts/generate_variant_qc_annotations.py
joint_calling-0.4.39.data/scripts/load_vqsr.py
joint_calling-0.4.39.data/scripts/make_finalised_mt.py
joint_calling-0.4.39.data/scripts/make_noref_mt.py
joint_calling-0.4.39.data/scripts/make_subset_mt.py
joint_calling-0.4.39.data/scripts/random_forest.py
joint_calling-0.4.39.data/scripts/release_vcf_export_chrom.py
joint_calling-0.4.39.data/scripts/sample_qc_flag_related.py
joint_calling-0.4.39.dist-info/LICENSE
joint_calling-0.4.39.dist-info/METADATA
joint_calling-0.4.39.dist-info/WHEEL
joint_calling-0.4.39.dist-info/top_level.txt
joint_calling-0.4.39.dist-info/RECORD
