Metadata-Version: 2.1
Name: joint-calling
Version: 0.4.39
Summary: Pipeline for joint calling, sample and variant QC for WGS germline variant calling data
Home-page: https://github.com/populationgenomics/joint-calling
License: MIT
Keywords: bioinformatics
Classifier: Environment :: Console
Classifier: Intended Audience :: Science/Research
Classifier: License :: OSI Approved :: GNU General Public License v3 (GPLv3)
Classifier: Natural Language :: English
Classifier: Operating System :: MacOS :: MacOS X
Classifier: Operating System :: POSIX
Classifier: Operating System :: Unix
Classifier: Programming Language :: Python
Classifier: Topic :: Scientific/Engineering
Classifier: Topic :: Scientific/Engineering :: Bio-Informatics
License-File: LICENSE
Requires-Dist: cpg-utils
Requires-Dist: pandas
Requires-Dist: hail (>=0.2.91)
Requires-Dist: click
Requires-Dist: google-cloud-storage
Requires-Dist: google-cloud-secret-manager
Requires-Dist: gnomad
Requires-Dist: analysis-runner
